patme/__init__.py
patme/buildtools/__init__.py
patme/buildtools/rce_releasecreator.py
patme/buildtools/release.py
patme/femtools/__init__.py
patme/femtools/abqmsgfilechecker.py
patme/femtools/fecall.py
patme/geometry/__init__.py
patme/geometry/area.py
patme/geometry/coordinatesystem.py
patme/geometry/intersect.py
patme/geometry/line.py
patme/geometry/misc.py
patme/geometry/plane.py
patme/geometry/rotate.py
patme/geometry/scale.py
patme/geometry/shape2d.py
patme/geometry/transformations.py
patme/geometry/translate.py
patme/mechanics/__init__.py
patme/mechanics/loads.py
patme/mechanics/material.py
patme/service/__init__.py
patme/service/decorators.py
patme/service/duration.py
patme/service/exceptionhook.py
patme/service/exceptions.py
patme/service/io/__init__.py
patme/service/io/basewriter.py
patme/service/logger.py
patme/service/mathutils.py
patme/service/misc.py
patme/service/moveimports.py
patme/service/stringutils.py
patme/service/systemutils.py
patme/sshtools/__init__.py
patme/sshtools/cara.py
patme/sshtools/clustercaller.py
patme/sshtools/facluster.py
patme/sshtools/sshcall.py
patme-0.4.9.dist-info/METADATA
patme-0.4.9.dist-info/WHEEL
patme-0.4.9.dist-info/entry_points.txt
patme-0.4.9.dist-info/licenses/LICENSE
patme-0.4.9.dist-info/licenses/LICENSES/MIT.txt
patme-0.4.9.dist-info/RECORD
