Metadata-Version: 2.4
Name: patme
Version: 0.4.9
Summary: Utilities for software builds, documentation, cluster interaction, calling fem tools, logging, exceptions and simple geometric and mechanical operations.
License-Expression: MIT
License-File: LICENSE
License-File: LICENSES/MIT.txt
Keywords: fem,logger,exception,geometry,mechanics,material,cluster
Author: Sebastian Freund
Author-email: sebastian.freund@dlr.de
Maintainer: Garbade, Marc
Maintainer-email: <marc.garbade@dlr.de>
Requires-Python: >=3.10,<4.0
Classifier: Programming Language :: Python :: 3
Classifier: Programming Language :: Python :: 3.10
Classifier: Programming Language :: Python :: 3.11
Classifier: Programming Language :: Python :: 3.12
Classifier: Programming Language :: Python :: 3.13
Classifier: Programming Language :: Python :: 3.14
Requires-Dist: importlib_metadata
Requires-Dist: numpy (<2)
Requires-Dist: scipy
Requires-Dist: sshconf
Requires-Dist: tomlkit
Project-URL: Changelog, https://gitlab.dlr.de/sy-stm/software/patme/-/blob/master/changelog.md
Project-URL: Documentation, https://sy-stm.pages.gitlab.dlr.de/software/patme/
Project-URL: Homepage, https://gitlab.dlr.de/fa_sw/patme
Project-URL: Repository, https://gitlab.dlr.de/fa_sw/patme
